{"is_source_file": false, "format": "", "description": "", "external_files": [], "external_methods": [], "published": [], "classes": [], "methods": [], "calls": [], "search-terms": [], "state": 2, "file_id": 27, "knowledge_revision": 58, "git_revision": "b2edc65e54407265e1acbb5b64e3127f48979279", "hash": "c920a648ebbae7e6a59dbf4b0909e329", "format-version": 4, "code-base-name": "frontend_qwik", "filename": "frontend_qwik/src/components/starter/infobox/infobox.module.css", "revision_history": [{"58": "b2edc65e54407265e1acbb5b64e3127f48979279"}]}